nuaim/__init__.py
nuaim/benchmark_presets.py
nuaim/model_factory.py
nuaim/core/__init__.py
nuaim/core/data_manager.py
nuaim/core/hyperparameter_manager.py
nuaim/core/logging_manager.py
nuaim/core/training_engine.py
nuaim/core/universal_model.py
nuaim/utils/__init__.py
nuaim/utils/activation_func_dict.py
nuaim/utils/dataset_dict.py
nuaim/utils/layer_dict.py
nuaim/utils/loss_func_dict.py
nuaim/utils/optimizer_dict.py
nuaim-1.0.0.dist-info/licenses/LICENSE
nuaim-1.0.0.dist-info/METADATA
nuaim-1.0.0.dist-info/WHEEL
nuaim-1.0.0.dist-info/top_level.txt
nuaim-1.0.0.dist-info/RECORD
