Metadata-Version: 2.4
Name: nuaim
Version: 1.0.0
Summary: NUAIM - Black-Box Generator for Meta-Variable Optimization.
Author-email: Noam Charette <charettenoam@gmail.com>
License-Expression: MIT
Project-URL: Homepage, https://github.com/NoVTeKa/NUAIM-BBO
Project-URL: Source, https://github.com/NoVTeKa/NUAIM-BBO
Project-URL: Documentation, https://github.com/NoVTeKa/NUAIM-BBO/blob/main/README.md
Project-URL: Issues, https://github.com/NoVTeKa/NUAIM-BBO/issues
Classifier: Development Status :: 3 - Alpha
Classifier: Intended Audience :: Science/Research
Classifier: Intended Audience :: Developers
Classifier: Programming Language :: Python :: 3
Classifier: Programming Language :: Python :: 3.8
Classifier: Programming Language :: Python :: 3.9
Classifier: Programming Language :: Python :: 3.10
Classifier: Programming Language :: Python :: 3.11
Classifier: Topic :: Scientific/Engineering :: Artificial Intelligence
Classifier: Topic :: Software Development :: Libraries :: Python Modules
Requires-Python: >=3.8
License-File: LICENSE
Requires-Dist: torch>=1.9.0
Requires-Dist: torchvision>=0.10.0
Requires-Dist: pytorch-ignite>=0.4.8
Requires-Dist: tqdm>=4.62.0
Requires-Dist: numpy>=1.21.0
Dynamic: license-file
